Metadata-Version: 2.4
Name: llama-index-readers-trello
Version: 0.4.1
Summary: llama-index readers trello integration
Author-email: Your Name <you@example.com>
Maintainer: bluzir
License-Expression: MIT
License-File: LICENSE
Keywords: trello
Requires-Python: <4.0,>=3.9
Requires-Dist: llama-index-core<0.15,>=0.13.0
Requires-Dist: py-trello<0.20,>=0.19.0
